README.rst
setup.py
neviseh/__init__.py
neviseh/pattern.py
neviseh/text.py
neviseh/utils.py
neviseh.egg-info/PKG-INFO
neviseh.egg-info/SOURCES.txt
neviseh.egg-info/dependency_links.txt
neviseh.egg-info/not-zip-safe
neviseh.egg-info/top_level.txt
neviseh/english/__init__.py
neviseh/english/base.py
neviseh/english/keymap.py
neviseh/english/numbers.py
neviseh/persian/__init__.py
neviseh/persian/base.py
neviseh/persian/calendar.py
neviseh/persian/keymap.py
neviseh/persian/numbers.py
neviseh/persian/text_normalization.py
neviseh/tests/__init__.py
neviseh/tests/test_english.py
neviseh/tests/test_persian.py
neviseh/tests/test_text.py