Metadata-Version: 1.1
Name: neviseh
Version: 0.1.3
Summary: Simple text processing tools in persian
Home-page: https://github.com/meyt/neviseh
Author: Mahdi Ghane.g
Author-email: UNKNOWN
License: MIT
Keywords: text-processing persian iran localization
Platform: UNKNOWN
Classifier: Development Status :: 3 - Alpha
Classifier: Intended Audience :: Developers
Classifier: License :: OSI Approved :: MIT License
Classifier: Operating System :: POSIX :: Linux
Classifier: Operating System :: Unix
Classifier: Natural Language :: Persian
Classifier: Programming Language :: Python :: 3.5
Classifier: Programming Language :: Python :: 3.6
Classifier: Topic :: Software Development :: Libraries
Classifier: Topic :: Text Processing
